{"otherData": {},"traceEvents":[{"cat":"function","dur":87099,"name":"void __cdecl Pixel::EditorLayer::OnUpdate(class Pixel::Timestep)","ph":"X","pid":0,"tid":4006434354,"ts":83425940907},{"cat":"function","dur":12679,"name":"void __cdecl Pixel::EditorLayer::OnUpdate(class Pixel::Timestep)","ph":"X","pid":0,"tid":4006434354,"ts":83426104220},{"cat":"function","dur":2987,"name":"void __cdecl Pixel::EditorLayer::OnUpdate(class Pixel::Timestep)","ph":"X","pid":0,"tid":4006434354,"ts":83426129541},{"cat":"function","dur":641,"name":"void __cdecl Pixel::EditorLayer::OnUpdate(class Pixel::Timestep)","ph":"X","pid":0,"tid":4006434354,"ts":83426146118},{"cat":"function","dur":578,"name":"void __cdecl Pixel::EditorLayer::OnUpdate(class Pixel::Timestep)","ph":"X","pid":0,"tid":4006434354,"ts":83426155396},{"cat":"function","dur":753,"name":"void __cdecl Pixel::EditorLayer::OnUpdate(class Pixel::Timestep)","ph":"X","pid":0,"tid":4006434354,"ts":83426163898},{"cat":"function","dur":665,"name":"void __cdecl Pixel::EditorLayer::OnUpdate(class Pixel::Timestep)","ph":"X","pid":0,"tid":4006434354,"ts":83426172039},{"cat":"function","dur":652,"name":"void __cdecl Pixel::EditorLayer::OnUpdate(class Pixel::Timestep)","ph":"X","pid":0,"tid":4006434354,"ts":83426180272},{"cat":"function","dur":602,"name":"void __cdecl Pixel::EditorLayer::OnUpdate(class Pixel::Timestep)","ph":"X","pid":0,"tid":4006434354,"ts":83426188376},{"cat":"function","dur":675,"name":"void __cdecl Pixel::EditorLayer::OnUpdate(class Pixel::Timestep)","ph":"X","pid":0,"tid":4006434354,"ts":83426197060},{"cat":"function","dur":724,"name":"void __cdecl Pixel::EditorLayer::OnUpdate(class Pixel::Timestep)","ph":"X","pid":0,"tid":4006434354,"ts":83426205714},{"cat":"function","dur":608,"name":"void __cdecl Pixel::EditorLayer::OnUpdate(class Pixel::Timestep)","ph":"X","pid":0,"tid":4006434354,"ts":83426213775},{"cat":"function","dur":647,"name":"void __cdecl Pixel::EditorLayer::OnUpdate(class Pixel::Timestep)","ph":"X","pid":0,"tid":4006434354,"ts":83426221943},{"cat":"function","dur":596,"name":"void __cdecl Pixel::EditorLayer::OnUpdate(class Pixel::Timestep)","ph":"X","pid":0,"tid":4006434354,"ts":83426230060},{"cat":"function","dur":772,"name":"void __cdecl Pixel::EditorLayer::OnUpdate(class Pixel::Timestep)","ph":"X","pid":0,"tid":4006434354,"ts":83426238511},{"cat":"function","dur":651,"name":"void __cdecl Pixel::EditorLayer::OnUpdate(class Pixel::Timestep)","ph":"X","pid":0,"tid":4006434354,"ts":83426246654},{"cat":"function","dur":661,"name":"void __cdecl Pixel::EditorLayer::OnUpdate(class Pixel::Timestep)","ph":"X","pid":0,"tid":4006434354,"ts":83426255082},{"cat":"function","dur":605,"name":"void __cdecl Pixel::EditorLayer::OnUpdate(class Pixel::Timestep)","ph":"X","pid":0,"tid":4006434354,"ts":83426263355},{"cat":"function","dur":709,"name":"void __cdecl Pixel::EditorLayer::OnUpdate(class Pixel::Timestep)","ph":"X","pid":0,"tid":4006434354,"ts":83426271780},{"cat":"function","dur":651,"name":"void __cdecl Pixel::EditorLayer::OnUpdate(class Pixel::Timestep)","ph":"X","pid":0,"tid":4006434354,"ts":83426280120},{"cat":"function","dur":676,"name":"void __cdecl Pixel::EditorLayer::OnUpdate(class Pixel::Timestep)","ph":"X","pid":0,"tid":4006434354,"ts":83426288422},{"cat":"function","dur":693,"name":"void __cdecl Pixel::EditorLayer::OnUpdate(class Pixel::Timestep)","ph":"X","pid":0,"tid":4006434354,"ts":83426296845},{"cat":"function","dur":689,"name":"void __cdecl Pixel::EditorLayer::OnUpdate(class Pixel::Timestep)","ph":"X","pid":0,"tid":4006434354,"ts":83426305371},{"cat":"function","dur":628,"name":"void __cdecl Pixel::EditorLayer::OnUpdate(class Pixel::Timestep)","ph":"X","pid":0,"tid":4006434354,"ts":83426313649},{"cat":"function","dur":660,"name":"void __cdecl Pixel::EditorLayer::OnUpdate(class Pixel::Timestep)","ph":"X","pid":0,"tid":4006434354,"ts":83426329693},{"cat":"function","dur":642,"name":"void __cdecl Pixel::EditorLayer::OnUpdate(class Pixel::Timestep)","ph":"X","pid":0,"tid":4006434354,"ts":83426338358},{"cat":"function","dur":565,"name":"void __cdecl Pixel::EditorLayer::OnUpdate(class Pixel::Timestep)","ph":"X","pid":0,"tid":4006434354,"ts":83426346639},{"cat":"function","dur":631,"name":"void __cdecl Pixel::EditorLayer::OnUpdate(class Pixel::Timestep)","ph":"X","pid":0,"tid":4006434354,"ts":83426355154},{"cat":"function","dur":607,"name":"void __cdecl Pixel::EditorLayer::OnUpdate(class Pixel::Timestep)","ph":"X","pid":0,"tid":4006434354,"ts":83426363499},{"cat":"function","dur":643,"name":"void __cdecl Pixel::EditorLayer::OnUpdate(class Pixel::Timestep)","ph":"X","pid":0,"tid":4006434354,"ts":83426372074},{"cat":"function","dur":662,"name":"void __cdecl Pixel::EditorLayer::OnUpdate(class Pixel::Timestep)","ph":"X","pid":0,"tid":4006434354,"ts":83426387772},{"cat":"function","dur":602,"name":"void __cdecl Pixel::EditorLayer::OnUpdate(class Pixel::Timestep)","ph":"X","pid":0,"tid":4006434354,"ts":83426404666},{"cat":"function","dur":623,"name":"void __cdecl Pixel::EditorLayer::OnUpdate(class Pixel::Timestep)","ph":"X","pid":0,"tid":4006434354,"ts":83426413434},{"cat":"function","dur":635,"name":"void __cdecl Pixel::EditorLayer::OnUpdate(class Pixel::Timestep)","ph":"X","pid":0,"tid":4006434354,"ts":83426422031},{"cat":"function","dur":550,"name":"void __cdecl Pixel::EditorLayer::OnUpdate(class Pixel::Timestep)","ph":"X","pid":0,"tid":4006434354,"ts":83426430005},{"cat":"function","dur":606,"name":"void __cdecl Pixel::EditorLayer::OnUpdate(class Pixel::Timestep)","ph":"X","pid":0,"tid":4006434354,"ts":83426438405},{"cat":"function","dur":596,"name":"void __cdecl Pixel::EditorLayer::OnUpdate(class Pixel::Timestep)","ph":"X","pid":0,"tid":4006434354,"ts":83426446718},{"cat":"function","dur":1131,"name":"void __cdecl Pixel::EditorLayer::OnUpdate(class Pixel::Timestep)","ph":"X","pid":0,"tid":4006434354,"ts":83426455169},{"cat":"function","dur":590,"name":"void __cdecl Pixel::EditorLayer::OnUpdate(class Pixel::Timestep)","ph":"X","pid":0,"tid":4006434354,"ts":83426463383},{"cat":"function","dur":598,"name":"void __cdecl Pixel::EditorLayer::OnUpdate(class Pixel::Timestep)","ph":"X","pid":0,"tid":4006434354,"ts":83426471596},{"cat":"function","dur":650,"name":"void __cdecl Pixel::EditorLayer::OnUpdate(class Pixel::Timestep)","ph":"X","pid":0,"tid":4006434354,"ts":83426480150},{"cat":"function","dur":611,"name":"void __cdecl Pixel::EditorLayer::OnUpdate(class Pixel::Timestep)","ph":"X","pid":0,"tid":4006434354,"ts":83426488324},{"cat":"function","dur":687,"name":"void __cdecl Pixel::EditorLayer::OnUpdate(class Pixel::Timestep)","ph":"X","pid":0,"tid":4006434354,"ts":83426496647},{"cat":"function","dur":585,"name":"void __cdecl Pixel::EditorLayer::OnUpdate(class Pixel::Timestep)","ph":"X","pid":0,"tid":4006434354,"ts":83426505478},{"cat":"function","dur":606,"name":"void __cdecl Pixel::EditorLayer::OnUpdate(class Pixel::Timestep)","ph":"X","pid":0,"tid":4006434354,"ts":83426513371},{"cat":"function","dur":619,"name":"void __cdecl Pixel::EditorLayer::OnUpdate(class Pixel::Timestep)","ph":"X","pid":0,"tid":4006434354,"ts":83426521652},{"cat":"function","dur":642,"name":"void __cdecl Pixel::EditorLayer::OnUpdate(class Pixel::Timestep)","ph":"X","pid":0,"tid":4006434354,"ts":83426537938},{"cat":"function","dur":721,"name":"void __cdecl Pixel::EditorLayer::OnUpdate(class Pixel::Timestep)","ph":"X","pid":0,"tid":4006434354,"ts":83426546691},{"cat":"function","dur":670,"name":"void __cdecl Pixel::EditorLayer::OnUpdate(class Pixel::Timestep)","ph":"X","pid":0,"tid":4006434354,"ts":83426555053},{"cat":"function","dur":597,"name":"void __cdecl Pixel::EditorLayer::OnUpdate(class Pixel::Timestep)","ph":"X","pid":0,"tid":4006434354,"ts":83426563653},{"cat":"function","dur":702,"name":"void __cdecl Pixel::EditorLayer::OnUpdate(class Pixel::Timestep)","ph":"X","pid":0,"tid":4006434354,"ts":83426571677},{"cat":"function","dur":585,"name":"void __cdecl Pixel::EditorLayer::OnUpdate(class Pixel::Timestep)","ph":"X","pid":0,"tid":4006434354,"ts":83426579886},{"cat":"function","dur":520,"name":"void __cdecl Pixel::EditorLayer::OnUpdate(class Pixel::Timestep)","ph":"X","pid":0,"tid":4006434354,"ts":83426588295},{"cat":"function","dur":583,"name":"void __cdecl Pixel::EditorLayer::OnUpdate(class Pixel::Timestep)","ph":"X","pid":0,"tid":4006434354,"ts":83426596715},{"cat":"function","dur":790,"name":"void __cdecl Pixel::EditorLayer::OnUpdate(class Pixel::Timestep)","ph":"X","pid":0,"tid":4006434354,"ts":83426605211},{"cat":"function","dur":739,"name":"void __cdecl Pixel::EditorLayer::OnUpdate(class Pixel::Timestep)","ph":"X","pid":0,"tid":4006434354,"ts":83426613924},{"cat":"function","dur":692,"name":"void __cdecl Pixel::EditorLayer::OnUpdate(class Pixel::Timestep)","ph":"X","pid":0,"tid":4006434354,"ts":83426621902},{"cat":"function","dur":562,"name":"void __cdecl Pixel::EditorLayer::OnUpdate(class Pixel::Timestep)","ph":"X","pid":0,"tid":4006434354,"ts":83426629970},{"cat":"function","dur":619,"name":"void __cdecl Pixel::EditorLayer::OnUpdate(class Pixel::Timestep)","ph":"X","pid":0,"tid":4006434354,"ts":83426638663},{"cat":"function","dur":634,"name":"void __cdecl Pixel::EditorLayer::OnUpdate(class Pixel::Timestep)","ph":"X","pid":0,"tid":4006434354,"ts":83426646693},{"cat":"function","dur":641,"name":"void __cdecl Pixel::EditorLayer::OnUpdate(class Pixel::Timestep)","ph":"X","pid":0,"tid":4006434354,"ts":83426655502},{"cat":"function","dur":564,"name":"void __cdecl Pixel::EditorLayer::OnUpdate(class Pixel::Timestep)","ph":"X","pid":0,"tid":4006434354,"ts":83426663600},{"cat":"function","dur":602,"name":"void __cdecl Pixel::EditorLayer::OnUpdate(class Pixel::Timestep)","ph":"X","pid":0,"tid":4006434354,"ts":83426671714},{"cat":"function","dur":615,"name":"void __cdecl Pixel::EditorLayer::OnUpdate(class Pixel::Timestep)","ph":"X","pid":0,"tid":4006434354,"ts":83426696104},{"cat":"function","dur":821,"name":"void __cdecl Pixel::EditorLayer::OnUpdate(class Pixel::Timestep)","ph":"X","pid":0,"tid":4006434354,"ts":83426705154},{"cat":"function","dur":678,"name":"void __cdecl Pixel::EditorLayer::OnUpdate(class Pixel::Timestep)","ph":"X","pid":0,"tid":4006434354,"ts":83426713409},{"cat":"function","dur":660,"name":"void __cdecl Pixel::EditorLayer::OnUpdate(class Pixel::Timestep)","ph":"X","pid":0,"tid":4006434354,"ts":83426721769},{"cat":"function","dur":698,"name":"void __cdecl Pixel::EditorLayer::OnUpdate(class Pixel::Timestep)","ph":"X","pid":0,"tid":4006434354,"ts":83426730029},{"cat":"function","dur":643,"name":"void __cdecl Pixel::EditorLayer::OnUpdate(class Pixel::Timestep)","ph":"X","pid":0,"tid":4006434354,"ts":83426738430},{"cat":"function","dur":629,"name":"void __cdecl Pixel::EditorLayer::OnUpdate(class Pixel::Timestep)","ph":"X","pid":0,"tid":4006434354,"ts":83426746819},{"cat":"function","dur":615,"name":"void __cdecl Pixel::EditorLayer::OnUpdate(class Pixel::Timestep)","ph":"X","pid":0,"tid":4006434354,"ts":83426754989},{"cat":"function","dur":656,"name":"void __cdecl Pixel::EditorLayer::OnUpdate(class Pixel::Timestep)","ph":"X","pid":0,"tid":4006434354,"ts":83426763687},{"cat":"function","dur":722,"name":"void __cdecl Pixel::EditorLayer::OnUpdate(class Pixel::Timestep)","ph":"X","pid":0,"tid":4006434354,"ts":83426774565},{"cat":"function","dur":595,"name":"void __cdecl Pixel::EditorLayer::OnUpdate(class Pixel::Timestep)","ph":"X","pid":0,"tid":4006434354,"ts":83426787731},{"cat":"function","dur":612,"name":"void __cdecl Pixel::EditorLayer::OnUpdate(class Pixel::Timestep)","ph":"X","pid":0,"tid":4006434354,"ts":83426805340},{"cat":"function","dur":602,"name":"void __cdecl Pixel::EditorLayer::OnUpdate(class Pixel::Timestep)","ph":"X","pid":0,"tid":4006434354,"ts":83426821078},{"cat":"function","dur":635,"name":"void __cdecl Pixel::EditorLayer::OnUpdate(class Pixel::Timestep)","ph":"X","pid":0,"tid":4006434354,"ts":83426830324},{"cat":"function","dur":570,"name":"void __cdecl Pixel::EditorLayer::OnUpdate(class Pixel::Timestep)","ph":"X","pid":0,"tid":4006434354,"ts":83426838254},{"cat":"function","dur":515,"name":"void __cdecl Pixel::EditorLayer::OnUpdate(class Pixel::Timestep)","ph":"X","pid":0,"tid":4006434354,"ts":83426846563},{"cat":"function","dur":593,"name":"void __cdecl Pixel::EditorLayer::OnUpdate(class Pixel::Timestep)","ph":"X","pid":0,"tid":4006434354,"ts":83426857665},{"cat":"function","dur":688,"name":"void __cdecl Pixel::EditorLayer::OnUpdate(class Pixel::Timestep)","ph":"X","pid":0,"tid":4006434354,"ts":83426871022},{"cat":"function","dur":639,"name":"void __cdecl Pixel::EditorLayer::OnUpdate(class Pixel::Timestep)","ph":"X","pid":0,"tid":4006434354,"ts":83426880337},{"cat":"function","dur":648,"name":"void __cdecl Pixel::EditorLayer::OnUpdate(class Pixel::Timestep)","ph":"X","pid":0,"tid":4006434354,"ts":83426889099},{"cat":"function","dur":667,"name":"void __cdecl Pixel::EditorLayer::OnUpdate(class Pixel::Timestep)","ph":"X","pid":0,"tid":4006434354,"ts":83426904856},{"cat":"function","dur":623,"name":"void __cdecl Pixel::EditorLayer::OnUpdate(class Pixel::Timestep)","ph":"X","pid":0,"tid":4006434354,"ts":83426913318},{"cat":"function","dur":646,"name":"void __cdecl Pixel::EditorLayer::OnUpdate(class Pixel::Timestep)","ph":"X","pid":0,"tid":4006434354,"ts":83426921704},{"cat":"function","dur":622,"name":"void __cdecl Pixel::EditorLayer::OnUpdate(class Pixel::Timestep)","ph":"X","pid":0,"tid":4006434354,"ts":83426929989},{"cat":"function","dur":736,"name":"void __cdecl Pixel::EditorLayer::OnUpdate(class Pixel::Timestep)","ph":"X","pid":0,"tid":4006434354,"ts":83426943741},{"cat":"function","dur":629,"name":"void __cdecl Pixel::EditorLayer::OnUpdate(class Pixel::Timestep)","ph":"X","pid":0,"tid":4006434354,"ts":83426954377},{"cat":"function","dur":614,"name":"void __cdecl Pixel::EditorLayer::OnUpdate(class Pixel::Timestep)","ph":"X","pid":0,"tid":4006434354,"ts":83426963467},{"cat":"function","dur":625,"name":"void __cdecl Pixel::EditorLayer::OnUpdate(class Pixel::Timestep)","ph":"X","pid":0,"tid":4006434354,"ts":83426971770},{"cat":"function","dur":607,"name":"void __cdecl Pixel::EditorLayer::OnUpdate(class Pixel::Timestep)","ph":"X","pid":0,"tid":4006434354,"ts":83426979986},{"cat":"function","dur":643,"name":"void __cdecl Pixel::EditorLayer::OnUpdate(class Pixel::Timestep)","ph":"X","pid":0,"tid":4006434354,"ts":83426988499},{"cat":"function","dur":689,"name":"void __cdecl Pixel::EditorLayer::OnUpdate(class Pixel::Timestep)","ph":"X","pid":0,"tid":4006434354,"ts":83426996626},{"cat":"function","dur":603,"name":"void __cdecl Pixel::EditorLayer::OnUpdate(class Pixel::Timestep)","ph":"X","pid":0,"tid":4006434354,"ts":83427005064},{"cat":"function","dur":598,"name":"void __cdecl Pixel::EditorLayer::OnUpdate(class Pixel::Timestep)","ph":"X","pid":0,"tid":4006434354,"ts":83427013360},{"cat":"function","dur":622,"name":"void __cdecl Pixel::EditorLayer::OnUpdate(class Pixel::Timestep)","ph":"X","pid":0,"tid":4006434354,"ts":83427021587},{"cat":"function","dur":682,"name":"void __cdecl Pixel::EditorLayer::OnUpdate(class Pixel::Timestep)","ph":"X","pid":0,"tid":4006434354,"ts":83427030497},{"cat":"function","dur":636,"name":"void __cdecl Pixel::EditorLayer::OnUpdate(class Pixel::Timestep)","ph":"X","pid":0,"tid":4006434354,"ts":83427038557},{"cat":"function","dur":643,"name":"void __cdecl Pixel::EditorLayer::OnUpdate(class Pixel::Timestep)","ph":"X","pid":0,"tid":4006434354,"ts":83427046724},{"cat":"function","dur":614,"name":"void __cdecl Pixel::EditorLayer::OnUpdate(class Pixel::Timestep)","ph":"X","pid":0,"tid":4006434354,"ts":83427054995},{"cat":"function","dur":597,"name":"void __cdecl Pixel::EditorLayer::OnUpdate(class Pixel::Timestep)","ph":"X","pid":0,"tid":4006434354,"ts":83427071050},{"cat":"function","dur":626,"name":"void __cdecl Pixel::EditorLayer::OnUpdate(class Pixel::Timestep)","ph":"X","pid":0,"tid":4006434354,"ts":83427079983},{"cat":"function","dur":587,"name":"void __cdecl Pixel::EditorLayer::OnUpdate(class Pixel::Timestep)","ph":"X","pid":0,"tid":4006434354,"ts":83427088230},{"cat":"function","dur":592,"name":"void __cdecl Pixel::EditorLayer::OnUpdate(class Pixel::Timestep)","ph":"X","pid":0,"tid":4006434354,"ts":83427096754},{"cat":"function","dur":568,"name":"void __cdecl Pixel::EditorLayer::OnUpdate(class Pixel::Timestep)","ph":"X","pid":0,"tid":4006434354,"ts":83427104907},{"cat":"function","dur":692,"name":"void __cdecl Pixel::EditorLayer::OnUpdate(class Pixel::Timestep)","ph":"X","pid":0,"tid":4006434354,"ts":83427113320},{"cat":"function","dur":652,"name":"void __cdecl Pixel::EditorLayer::OnUpdate(class Pixel::Timestep)","ph":"X","pid":0,"tid":4006434354,"ts":83427121702},{"cat":"function","dur":654,"name":"void __cdecl Pixel::EditorLayer::OnUpdate(class Pixel::Timestep)","ph":"X","pid":0,"tid":4006434354,"ts":83427137723},{"cat":"function","dur":468,"name":"void __cdecl Pixel::EditorLayer::OnUpdate(class Pixel::Timestep)","ph":"X","pid":0,"tid":4006434354,"ts":83427146466},{"cat":"function","dur":634,"name":"void __cdecl Pixel::EditorLayer::OnUpdate(class Pixel::Timestep)","ph":"X","pid":0,"tid":4006434354,"ts":83427155156},{"cat":"function","dur":684,"name":"void __cdecl Pixel::EditorLayer::OnUpdate(class Pixel::Timestep)","ph":"X","pid":0,"tid":4006434354,"ts":83427171273},{"cat":"function","dur":650,"name":"void __cdecl Pixel::EditorLayer::OnUpdate(class Pixel::Timestep)","ph":"X","pid":0,"tid":4006434354,"ts":83427180214},{"cat":"function","dur":640,"name":"void __cdecl Pixel::EditorLayer::OnUpdate(class Pixel::Timestep)","ph":"X","pid":0,"tid":4006434354,"ts":83427188404},{"cat":"function","dur":637,"name":"void __cdecl Pixel::EditorLayer::OnUpdate(class Pixel::Timestep)","ph":"X","pid":0,"tid":4006434354,"ts":83427196575},{"cat":"function","dur":668,"name":"void __cdecl Pixel::EditorLayer::OnUpdate(class Pixel::Timestep)","ph":"X","pid":0,"tid":4006434354,"ts":83427204968},{"cat":"function","dur":611,"name":"void __cdecl Pixel::EditorLayer::OnUpdate(class Pixel::Timestep)","ph":"X","pid":0,"tid":4006434354,"ts":83427213310},{"cat":"function","dur":639,"name":"void __cdecl Pixel::EditorLayer::OnUpdate(class Pixel::Timestep)","ph":"X","pid":0,"tid":4006434354,"ts":83427221768},{"cat":"function","dur":640,"name":"void __cdecl Pixel::EditorLayer::OnUpdate(class Pixel::Timestep)","ph":"X","pid":0,"tid":4006434354,"ts":83427230199},{"cat":"function","dur":614,"name":"void __cdecl Pixel::EditorLayer::OnUpdate(class Pixel::Timestep)","ph":"X","pid":0,"tid":4006434354,"ts":83427238331},{"cat":"function","dur":669,"name":"void __cdecl Pixel::EditorLayer::OnUpdate(class Pixel::Timestep)","ph":"X","pid":0,"tid":4006434354,"ts":83427246882},{"cat":"function","dur":661,"name":"void __cdecl Pixel::EditorLayer::OnUpdate(class Pixel::Timestep)","ph":"X","pid":0,"tid":4006434354,"ts":83427255120},{"cat":"function","dur":813,"name":"void __cdecl Pixel::EditorLayer::OnUpdate(class Pixel::Timestep)","ph":"X","pid":0,"tid":4006434354,"ts":83427263352},{"cat":"function","dur":639,"name":"void __cdecl Pixel::EditorLayer::OnUpdate(class Pixel::Timestep)","ph":"X","pid":0,"tid":4006434354,"ts":83427272108},{"cat":"function","dur":666,"name":"void __cdecl Pixel::EditorLayer::OnUpdate(class Pixel::Timestep)","ph":"X","pid":0,"tid":4006434354,"ts":83427280247},{"cat":"function","dur":728,"name":"void __cdecl Pixel::EditorLayer::OnUpdate(class Pixel::Timestep)","ph":"X","pid":0,"tid":4006434354,"ts":83427288539},{"cat":"function","dur":820,"name":"void __cdecl Pixel::EditorLayer::OnUpdate(class Pixel::Timestep)","ph":"X","pid":0,"tid":4006434354,"ts":83427297380},{"cat":"function","dur":607,"name":"void __cdecl Pixel::EditorLayer::OnUpdate(class Pixel::Timestep)","ph":"X","pid":0,"tid":4006434354,"ts":83427312723},{"cat":"function","dur":645,"name":"void __cdecl Pixel::EditorLayer::OnUpdate(class Pixel::Timestep)","ph":"X","pid":0,"tid":4006434354,"ts":83427321797},{"cat":"function","dur":642,"name":"void __cdecl Pixel::EditorLayer::OnUpdate(class Pixel::Timestep)","ph":"X","pid":0,"tid":4006434354,"ts":83427330222},{"cat":"function","dur":684,"name":"void __cdecl Pixel::EditorLayer::OnUpdate(class Pixel::Timestep)","ph":"X","pid":0,"tid":4006434354,"ts":83427338395},{"cat":"function","dur":628,"name":"void __cdecl Pixel::EditorLayer::OnUpdate(class Pixel::Timestep)","ph":"X","pid":0,"tid":4006434354,"ts":83427354417},{"cat":"function","dur":764,"name":"void __cdecl Pixel::EditorLayer::OnUpdate(class Pixel::Timestep)","ph":"X","pid":0,"tid":4006434354,"ts":83427363668},{"cat":"function","dur":600,"name":"void __cdecl Pixel::EditorLayer::OnUpdate(class Pixel::Timestep)","ph":"X","pid":0,"tid":4006434354,"ts":83427379576},{"cat":"function","dur":760,"name":"void __cdecl Pixel::EditorLayer::OnUpdate(class Pixel::Timestep)","ph":"X","pid":0,"tid":4006434354,"ts":83427388705},{"cat":"function","dur":731,"name":"void __cdecl Pixel::EditorLayer::OnUpdate(class Pixel::Timestep)","ph":"X","pid":0,"tid":4006434354,"ts":83427404516},{"cat":"function","dur":501,"name":"void __cdecl Pixel::EditorLayer::OnUpdate(class Pixel::Timestep)","ph":"X","pid":0,"tid":4006434354,"ts":83427413545},{"cat":"function","dur":670,"name":"void __cdecl Pixel::EditorLayer::OnUpdate(class Pixel::Timestep)","ph":"X","pid":0,"tid":4006434354,"ts":83427429820},{"cat":"function","dur":650,"name":"void __cdecl Pixel::EditorLayer::OnUpdate(class Pixel::Timestep)","ph":"X","pid":0,"tid":4006434354,"ts":83427438295},{"cat":"function","dur":667,"name":"void __cdecl Pixel::EditorLayer::OnUpdate(class Pixel::Timestep)","ph":"X","pid":0,"tid":4006434354,"ts":83427446715},{"cat":"function","dur":703,"name":"void __cdecl Pixel::EditorLayer::OnUpdate(class Pixel::Timestep)","ph":"X","pid":0,"tid":4006434354,"ts":83427455056},{"cat":"function","dur":566,"name":"void __cdecl Pixel::EditorLayer::OnUpdate(class Pixel::Timestep)","ph":"X","pid":0,"tid":4006434354,"ts":83427463216},{"cat":"function","dur":625,"name":"void __cdecl Pixel::EditorLayer::OnUpdate(class Pixel::Timestep)","ph":"X","pid":0,"tid":4006434354,"ts":83427471582},{"cat":"function","dur":621,"name":"void __cdecl Pixel::EditorLayer::OnUpdate(class Pixel::Timestep)","ph":"X","pid":0,"tid":4006434354,"ts":83427480057},{"cat":"function","dur":584,"name":"void __cdecl Pixel::EditorLayer::OnUpdate(class Pixel::Timestep)","ph":"X","pid":0,"tid":4006434354,"ts":83427488241},{"cat":"function","dur":754,"name":"void __cdecl Pixel::EditorLayer::OnUpdate(class Pixel::Timestep)","ph":"X","pid":0,"tid":4006434354,"ts":83427496823},{"cat":"function","dur":650,"name":"void __cdecl Pixel::EditorLayer::OnUpdate(class Pixel::Timestep)","ph":"X","pid":0,"tid":4006434354,"ts":83427512627},{"cat":"function","dur":595,"name":"void __cdecl Pixel::EditorLayer::OnUpdate(class Pixel::Timestep)","ph":"X","pid":0,"tid":4006434354,"ts":83427522090},{"cat":"function","dur":988,"name":"void __cdecl Pixel::EditorLayer::OnUpdate(class Pixel::Timestep)","ph":"X","pid":0,"tid":4006434354,"ts":83427530491},{"cat":"function","dur":857,"name":"void __cdecl Pixel::EditorLayer::OnUpdate(class Pixel::Timestep)","ph":"X","pid":0,"tid":4006434354,"ts":83427546758},{"cat":"function","dur":673,"name":"void __cdecl Pixel::EditorLayer::OnUpdate(class Pixel::Timestep)","ph":"X","pid":0,"tid":4006434354,"ts":83427555010},{"cat":"function","dur":718,"name":"void __cdecl Pixel::EditorLayer::OnUpdate(class Pixel::Timestep)","ph":"X","pid":0,"tid":4006434354,"ts":83427563673},{"cat":"function","dur":602,"name":"void __cdecl Pixel::EditorLayer::OnUpdate(class Pixel::Timestep)","ph":"X","pid":0,"tid":4006434354,"ts":83427571663},{"cat":"function","dur":558,"name":"void __cdecl Pixel::EditorLayer::OnUpdate(class Pixel::Timestep)","ph":"X","pid":0,"tid":4006434354,"ts":83427580205},{"cat":"function","dur":630,"name":"void __cdecl Pixel::EditorLayer::OnUpdate(class Pixel::Timestep)","ph":"X","pid":0,"tid":4006434354,"ts":83427588250},{"cat":"function","dur":617,"name":"void __cdecl Pixel::EditorLayer::OnUpdate(class Pixel::Timestep)","ph":"X","pid":0,"tid":4006434354,"ts":83427604789},{"cat":"function","dur":606,"name":"void __cdecl Pixel::EditorLayer::OnUpdate(class Pixel::Timestep)","ph":"X","pid":0,"tid":4006434354,"ts":83427613524},{"cat":"function","dur":630,"name":"void __cdecl Pixel::EditorLayer::OnUpdate(class Pixel::Timestep)","ph":"X","pid":0,"tid":4006434354,"ts":83427621688},{"cat":"function","dur":637,"name":"void __cdecl Pixel::EditorLayer::OnUpdate(class Pixel::Timestep)","ph":"X","pid":0,"tid":4006434354,"ts":83427630179},{"cat":"function","dur":651,"name":"void __cdecl Pixel::EditorLayer::OnUpdate(class Pixel::Timestep)","ph":"X","pid":0,"tid":4006434354,"ts":83427638299},{"cat":"function","dur":663,"name":"void __cdecl Pixel::EditorLayer::OnUpdate(class Pixel::Timestep)","ph":"X","pid":0,"tid":4006434354,"ts":83427646693},{"cat":"function","dur":663,"name":"void __cdecl Pixel::EditorLayer::OnUpdate(class Pixel::Timestep)","ph":"X","pid":0,"tid":4006434354,"ts":83427654934},{"cat":"function","dur":593,"name":"void __cdecl Pixel::EditorLayer::OnUpdate(class Pixel::Timestep)","ph":"X","pid":0,"tid":4006434354,"ts":83427663280},{"cat":"function","dur":594,"name":"void __cdecl Pixel::EditorLayer::OnUpdate(class Pixel::Timestep)","ph":"X","pid":0,"tid":4006434354,"ts":83427672262},{"cat":"function","dur":652,"name":"void __cdecl Pixel::EditorLayer::OnUpdate(class Pixel::Timestep)","ph":"X","pid":0,"tid":4006434354,"ts":83427680241},{"cat":"function","dur":584,"name":"void __cdecl Pixel::EditorLayer::OnUpdate(class Pixel::Timestep)","ph":"X","pid":0,"tid":4006434354,"ts":83427688253},{"cat":"function","dur":652,"name":"void __cdecl Pixel::EditorLayer::OnUpdate(class Pixel::Timestep)","ph":"X","pid":0,"tid":4006434354,"ts":83427696693},{"cat":"function","dur":900,"name":"void __cdecl Pixel::EditorLayer::OnUpdate(class Pixel::Timestep)","ph":"X","pid":0,"tid":4006434354,"ts":83427704879},{"cat":"function","dur":595,"name":"void __cdecl Pixel::EditorLayer::OnUpdate(class Pixel::Timestep)","ph":"X","pid":0,"tid":4006434354,"ts":83427713720},{"cat":"function","dur":1226,"name":"void __cdecl Pixel::EditorLayer::OnUpdate(class Pixel::Timestep)","ph":"X","pid":0,"tid":4006434354,"ts":83427730284},{"cat":"function","dur":615,"name":"void __cdecl Pixel::EditorLayer::OnUpdate(class Pixel::Timestep)","ph":"X","pid":0,"tid":4006434354,"ts":83427746554},{"cat":"function","dur":641,"name":"void __cdecl Pixel::EditorLayer::OnUpdate(class Pixel::Timestep)","ph":"X","pid":0,"tid":4006434354,"ts":83427754901},{"cat":"function","dur":581,"name":"void __cdecl Pixel::EditorLayer::OnUpdate(class Pixel::Timestep)","ph":"X","pid":0,"tid":4006434354,"ts":83427763122},{"cat":"function","dur":605,"name":"void __cdecl Pixel::EditorLayer::OnUpdate(class Pixel::Timestep)","ph":"X","pid":0,"tid":4006434354,"ts":83427779318},{"cat":"function","dur":663,"name":"void __cdecl Pixel::EditorLayer::OnUpdate(class Pixel::Timestep)","ph":"X","pid":0,"tid":4006434354,"ts":83427789168},{"cat":"function","dur":670,"name":"void __cdecl Pixel::EditorLayer::OnUpdate(class Pixel::Timestep)","ph":"X","pid":0,"tid":4006434354,"ts":83427804961},{"cat":"function","dur":819,"name":"void __cdecl Pixel::EditorLayer::OnUpdate(class Pixel::Timestep)","ph":"X","pid":0,"tid":4006434354,"ts":83427821892},{"cat":"function","dur":805,"name":"void __cdecl Pixel::EditorLayer::OnUpdate(class Pixel::Timestep)","ph":"X","pid":0,"tid":4006434354,"ts":83427838691},{"cat":"function","dur":582,"name":"void __cdecl Pixel::EditorLayer::OnUpdate(class Pixel::Timestep)","ph":"X","pid":0,"tid":4006434354,"ts":83427855107},{"cat":"function","dur":646,"name":"void __cdecl Pixel::EditorLayer::OnUpdate(class Pixel::Timestep)","ph":"X","pid":0,"tid":4006434354,"ts":83427863293},{"cat":"function","dur":665,"name":"void __cdecl Pixel::EditorLayer::OnUpdate(class Pixel::Timestep)","ph":"X","pid":0,"tid":4006434354,"ts":83427871602},{"cat":"function","dur":638,"name":"void __cdecl Pixel::EditorLayer::OnUpdate(class Pixel::Timestep)","ph":"X","pid":0,"tid":4006434354,"ts":83427887601},{"cat":"function","dur":730,"name":"void __cdecl Pixel::EditorLayer::OnUpdate(class Pixel::Timestep)","ph":"X","pid":0,"tid":4006434354,"ts":83427904222},{"cat":"function","dur":635,"name":"void __cdecl Pixel::EditorLayer::OnUpdate(class Pixel::Timestep)","ph":"X","pid":0,"tid":4006434354,"ts":83427913273},{"cat":"function","dur":721,"name":"void __cdecl Pixel::EditorLayer::OnUpdate(class Pixel::Timestep)","ph":"X","pid":0,"tid":4006434354,"ts":83427922006},{"cat":"function","dur":644,"name":"void __cdecl Pixel::EditorLayer::OnUpdate(class Pixel::Timestep)","ph":"X","pid":0,"tid":4006434354,"ts":83427930112},{"cat":"function","dur":551,"name":"void __cdecl Pixel::EditorLayer::OnUpdate(class Pixel::Timestep)","ph":"X","pid":0,"tid":4006434354,"ts":83427939456},{"cat":"function","dur":560,"name":"void __cdecl Pixel::EditorLayer::OnUpdate(class Pixel::Timestep)","ph":"X","pid":0,"tid":4006434354,"ts":83427954228},{"cat":"function","dur":653,"name":"void __cdecl Pixel::EditorLayer::OnUpdate(class Pixel::Timestep)","ph":"X","pid":0,"tid":4006434354,"ts":83427963212},{"cat":"function","dur":551,"name":"void __cdecl Pixel::EditorLayer::OnUpdate(class Pixel::Timestep)","ph":"X","pid":0,"tid":4006434354,"ts":83427971546},{"cat":"function","dur":673,"name":"void __cdecl Pixel::EditorLayer::OnUpdate(class Pixel::Timestep)","ph":"X","pid":0,"tid":4006434354,"ts":83427979961},{"cat":"function","dur":610,"name":"void __cdecl Pixel::EditorLayer::OnUpdate(class Pixel::Timestep)","ph":"X","pid":0,"tid":4006434354,"ts":83427988308},{"cat":"function","dur":623,"name":"void __cdecl Pixel::EditorLayer::OnUpdate(class Pixel::Timestep)","ph":"X","pid":0,"tid":4006434354,"ts":83427996555},{"cat":"function","dur":601,"name":"void __cdecl Pixel::EditorLayer::OnUpdate(class Pixel::Timestep)","ph":"X","pid":0,"tid":4006434354,"ts":83428004843},{"cat":"function","dur":624,"name":"void __cdecl Pixel::EditorLayer::OnUpdate(class Pixel::Timestep)","ph":"X","pid":0,"tid":4006434354,"ts":83428013235},{"cat":"function","dur":683,"name":"void __cdecl Pixel::EditorLayer::OnUpdate(class Pixel::Timestep)","ph":"X","pid":0,"tid":4006434354,"ts":83428029433},{"cat":"function","dur":616,"name":"void __cdecl Pixel::EditorLayer::OnUpdate(class Pixel::Timestep)","ph":"X","pid":0,"tid":4006434354,"ts":83428038114},{"cat":"function","dur":688,"name":"void __cdecl Pixel::EditorLayer::OnUpdate(class Pixel::Timestep)","ph":"X","pid":0,"tid":4006434354,"ts":83428046437},{"cat":"function","dur":667,"name":"void __cdecl Pixel::EditorLayer::OnUpdate(class Pixel::Timestep)","ph":"X","pid":0,"tid":4006434354,"ts":83428054854},{"cat":"function","dur":984,"name":"void __cdecl Pixel::EditorLayer::OnUpdate(class Pixel::Timestep)","ph":"X","pid":0,"tid":4006434354,"ts":83428063224},{"cat":"function","dur":1065,"name":"void __cdecl Pixel::EditorLayer::OnUpdate(class Pixel::Timestep)","ph":"X","pid":0,"tid":4006434354,"ts":83428071849},{"cat":"function","dur":711,"name":"void __cdecl Pixel::EditorLayer::OnUpdate(class Pixel::Timestep)","ph":"X","pid":0,"tid":4006434354,"ts":83428079989},{"cat":"function","dur":631,"name":"void __cdecl Pixel::EditorLayer::OnUpdate(class Pixel::Timestep)","ph":"X","pid":0,"tid":4006434354,"ts":83428088113},{"cat":"function","dur":608,"name":"void __cdecl Pixel::EditorLayer::OnUpdate(class Pixel::Timestep)","ph":"X","pid":0,"tid":4006434354,"ts":83428096775},{"cat":"function","dur":610,"name":"void __cdecl Pixel::EditorLayer::OnUpdate(class Pixel::Timestep)","ph":"X","pid":0,"tid":4006434354,"ts":83428104852},{"cat":"function","dur":809,"name":"void __cdecl Pixel::EditorLayer::OnUpdate(class Pixel::Timestep)","ph":"X","pid":0,"tid":4006434354,"ts":83428113412},{"cat":"function","dur":721,"name":"void __cdecl Pixel::EditorLayer::OnUpdate(class Pixel::Timestep)","ph":"X","pid":0,"tid":4006434354,"ts":83428121906},{"cat":"function","dur":625,"name":"void __cdecl Pixel::EditorLayer::OnUpdate(class Pixel::Timestep)","ph":"X","pid":0,"tid":4006434354,"ts":83428137866},{"cat":"function","dur":653,"name":"void __cdecl Pixel::EditorLayer::OnUpdate(class Pixel::Timestep)","ph":"X","pid":0,"tid":4006434354,"ts":83428146650},{"cat":"function","dur":672,"name":"void __cdecl Pixel::EditorLayer::OnUpdate(class Pixel::Timestep)","ph":"X","pid":0,"tid":4006434354,"ts":83428154785},{"cat":"function","dur":532,"name":"void __cdecl Pixel::EditorLayer::OnUpdate(class Pixel::Timestep)","ph":"X","pid":0,"tid":4006434354,"ts":83428163069},{"cat":"function","dur":623,"name":"void __cdecl Pixel::EditorLayer::OnUpdate(class Pixel::Timestep)","ph":"X","pid":0,"tid":4006434354,"ts":83428172211},{"cat":"function","dur":716,"name":"void __cdecl Pixel::EditorLayer::OnUpdate(class Pixel::Timestep)","ph":"X","pid":0,"tid":4006434354,"ts":83428187615},{"cat":"function","dur":677,"name":"void __cdecl Pixel::EditorLayer::OnUpdate(class Pixel::Timestep)","ph":"X","pid":0,"tid":4006434354,"ts":83428196543},{"cat":"function","dur":812,"name":"void __cdecl Pixel::EditorLayer::OnUpdate(class Pixel::Timestep)","ph":"X","pid":0,"tid":4006434354,"ts":83428204980},{"cat":"function","dur":610,"name":"void __cdecl Pixel::EditorLayer::OnUpdate(class Pixel::Timestep)","ph":"X","pid":0,"tid":4006434354,"ts":83428213207},{"cat":"function","dur":709,"name":"void __cdecl Pixel::EditorLayer::OnUpdate(class Pixel::Timestep)","ph":"X","pid":0,"tid":4006434354,"ts":83428221670},{"cat":"function","dur":687,"name":"void __cdecl Pixel::EditorLayer::OnUpdate(class Pixel::Timestep)","ph":"X","pid":0,"tid":4006434354,"ts":83428229967},{"cat":"function","dur":847,"name":"void __cdecl Pixel::EditorLayer::OnUpdate(class Pixel::Timestep)","ph":"X","pid":0,"tid":4006434354,"ts":83428238181},{"cat":"function","dur":775,"name":"void __cdecl Pixel::EditorLayer::OnUpdate(class Pixel::Timestep)","ph":"X","pid":0,"tid":4006434354,"ts":83428246747},{"cat":"function","dur":695,"name":"void __cdecl Pixel::EditorLayer::OnUpdate(class Pixel::Timestep)","ph":"X","pid":0,"tid":4006434354,"ts":83428255135},{"cat":"function","dur":730,"name":"void __cdecl Pixel::EditorLayer::OnUpdate(class Pixel::Timestep)","ph":"X","pid":0,"tid":4006434354,"ts":83428264358},{"cat":"function","dur":653,"name":"void __cdecl Pixel::EditorLayer::OnUpdate(class Pixel::Timestep)","ph":"X","pid":0,"tid":4006434354,"ts":83428279811},{"cat":"function","dur":656,"name":"void __cdecl Pixel::EditorLayer::OnUpdate(class Pixel::Timestep)","ph":"X","pid":0,"tid":4006434354,"ts":83428288409},{"cat":"function","dur":731,"name":"void __cdecl Pixel::EditorLayer::OnUpdate(class Pixel::Timestep)","ph":"X","pid":0,"tid":4006434354,"ts":83428297060},{"cat":"function","dur":697,"name":"void __cdecl Pixel::EditorLayer::OnUpdate(class Pixel::Timestep)","ph":"X","pid":0,"tid":4006434354,"ts":83428312664},{"cat":"function","dur":738,"name":"void __cdecl Pixel::EditorLayer::OnUpdate(class Pixel::Timestep)","ph":"X","pid":0,"tid":4006434354,"ts":83428321486},{"cat":"function","dur":681,"name":"void __cdecl Pixel::EditorLayer::OnUpdate(class Pixel::Timestep)","ph":"X","pid":0,"tid":4006434354,"ts":83428330166},{"cat":"function","dur":686,"name":"void __cdecl Pixel::EditorLayer::OnUpdate(class Pixel::Timestep)","ph":"X","pid":0,"tid":4006434354,"ts":83428346302},{"cat":"function","dur":621,"name":"void __cdecl Pixel::EditorLayer::OnUpdate(class Pixel::Timestep)","ph":"X","pid":0,"tid":4006434354,"ts":83428354950},{"cat":"function","dur":672,"name":"void __cdecl Pixel::EditorLayer::OnUpdate(class Pixel::Timestep)","ph":"X","pid":0,"tid":4006434354,"ts":83428363149},{"cat":"function","dur":614,"name":"void __cdecl Pixel::EditorLayer::OnUpdate(class Pixel::Timestep)","ph":"X","pid":0,"tid":4006434354,"ts":83428371556},{"cat":"function","dur":600,"name":"void __cdecl Pixel::EditorLayer::OnUpdate(class Pixel::Timestep)","ph":"X","pid":0,"tid":4006434354,"ts":83428387624},{"cat":"function","dur":535,"name":"void __cdecl Pixel::EditorLayer::OnUpdate(class Pixel::Timestep)","ph":"X","pid":0,"tid":4006434354,"ts":83428396573},{"cat":"function","dur":665,"name":"void __cdecl Pixel::EditorLayer::OnUpdate(class Pixel::Timestep)","ph":"X","pid":0,"tid":4006434354,"ts":83428404889},{"cat":"function","dur":683,"name":"void __cdecl Pixel::EditorLayer::OnUpdate(class Pixel::Timestep)","ph":"X","pid":0,"tid":4006434354,"ts":83428413219},{"cat":"function","dur":779,"name":"void __cdecl Pixel::EditorLayer::OnUpdate(class Pixel::Timestep)","ph":"X","pid":0,"tid":4006434354,"ts":83428421856},{"cat":"function","dur":704,"name":"void __cdecl Pixel::EditorLayer::OnUpdate(class Pixel::Timestep)","ph":"X","pid":0,"tid":4006434354,"ts":83428429978},{"cat":"function","dur":670,"name":"void __cdecl Pixel::EditorLayer::OnUpdate(class Pixel::Timestep)","ph":"X","pid":0,"tid":4006434354,"ts":83428438236},{"cat":"function","dur":591,"name":"void __cdecl Pixel::EditorLayer::OnUpdate(class Pixel::Timestep)","ph":"X","pid":0,"tid":4006434354,"ts":83428447053},{"cat":"function","dur":608,"name":"void __cdecl Pixel::EditorLayer::OnUpdate(class Pixel::Timestep)","ph":"X","pid":0,"tid":4006434354,"ts":83428456120},{"cat":"function","dur":624,"name":"void __cdecl Pixel::EditorLayer::OnUpdate(class Pixel::Timestep)","ph":"X","pid":0,"tid":4006434354,"ts":83428463363},{"cat":"function","dur":1305,"name":"void __cdecl Pixel::EditorLayer::OnUpdate(class Pixel::Timestep)","ph":"X","pid":0,"tid":4006434354,"ts":83428471727},{"cat":"function","dur":602,"name":"void __cdecl Pixel::EditorLayer::OnUpdate(class Pixel::Timestep)","ph":"X","pid":0,"tid":4006434354,"ts":83428487544},{"cat":"function","dur":598,"name":"void __cdecl Pixel::EditorLayer::OnUpdate(class Pixel::Timestep)","ph":"X","pid":0,"tid":4006434354,"ts":83428496471},{"cat":"function","dur":640,"name":"void __cdecl Pixel::EditorLayer::OnUpdate(class Pixel::Timestep)","ph":"X","pid":0,"tid":4006434354,"ts":83428504813},{"cat":"function","dur":612,"name":"void __cdecl Pixel::EditorLayer::OnUpdate(class Pixel::Timestep)","ph":"X","pid":0,"tid":4006434354,"ts":83428513095},{"cat":"function","dur":668,"name":"void __cdecl Pixel::EditorLayer::OnUpdate(class Pixel::Timestep)","ph":"X","pid":0,"tid":4006434354,"ts":83428521594},{"cat":"function","dur":732,"name":"void __cdecl Pixel::EditorLayer::OnUpdate(class Pixel::Timestep)","ph":"X","pid":0,"tid":4006434354,"ts":83428530017},{"cat":"function","dur":719,"name":"void __cdecl Pixel::EditorLayer::OnUpdate(class Pixel::Timestep)","ph":"X","pid":0,"tid":4006434354,"ts":83428538896},{"cat":"function","dur":668,"name":"void __cdecl Pixel::EditorLayer::OnUpdate(class Pixel::Timestep)","ph":"X","pid":0,"tid":4006434354,"ts":83428546784},{"cat":"function","dur":654,"name":"void __cdecl Pixel::EditorLayer::OnUpdate(class Pixel::Timestep)","ph":"X","pid":0,"tid":4006434354,"ts":83428554995},{"cat":"function","dur":685,"name":"void __cdecl Pixel::EditorLayer::OnUpdate(class Pixel::Timestep)","ph":"X","pid":0,"tid":4006434354,"ts":83428563180},{"cat":"function","dur":661,"name":"void __cdecl Pixel::EditorLayer::OnUpdate(class Pixel::Timestep)","ph":"X","pid":0,"tid":4006434354,"ts":83428571494},{"cat":"function","dur":633,"name":"void __cdecl Pixel::EditorLayer::OnUpdate(class Pixel::Timestep)","ph":"X","pid":0,"tid":4006434354,"ts":83428579879},{"cat":"function","dur":647,"name":"void __cdecl Pixel::EditorLayer::OnUpdate(class Pixel::Timestep)","ph":"X","pid":0,"tid":4006434354,"ts":83428588252},{"cat":"function","dur":624,"name":"void __cdecl Pixel::EditorLayer::OnUpdate(class Pixel::Timestep)","ph":"X","pid":0,"tid":4006434354,"ts":83428596628},{"cat":"function","dur":589,"name":"void __cdecl Pixel::EditorLayer::OnUpdate(class Pixel::Timestep)","ph":"X","pid":0,"tid":4006434354,"ts":83428605653},{"cat":"function","dur":727,"name":"void __cdecl Pixel::EditorLayer::OnUpdate(class Pixel::Timestep)","ph":"X","pid":0,"tid":4006434354,"ts":83428620928},{"cat":"function","dur":1469,"name":"void __cdecl Pixel::EditorLayer::OnUpdate(class Pixel::Timestep)","ph":"X","pid":0,"tid":4006434354,"ts":83428630172},{"cat":"function","dur":576,"name":"void __cdecl Pixel::EditorLayer::OnUpdate(class Pixel::Timestep)","ph":"X","pid":0,"tid":4006434354,"ts":83428638023},{"cat":"function","dur":657,"name":"void __cdecl Pixel::EditorLayer::OnUpdate(class Pixel::Timestep)","ph":"X","pid":0,"tid":4006434354,"ts":83428646495},{"cat":"function","dur":572,"name":"void __cdecl Pixel::EditorLayer::OnUpdate(class Pixel::Timestep)","ph":"X","pid":0,"tid":4006434354,"ts":83428655063},{"cat":"function","dur":614,"name":"void __cdecl Pixel::EditorLayer::OnUpdate(class Pixel::Timestep)","ph":"X","pid":0,"tid":4006434354,"ts":83428662977},{"cat":"function","dur":664,"name":"void __cdecl Pixel::EditorLayer::OnUpdate(class Pixel::Timestep)","ph":"X","pid":0,"tid":4006434354,"ts":83428671559},{"cat":"function","dur":714,"name":"void __cdecl Pixel::EditorLayer::OnUpdate(class Pixel::Timestep)","ph":"X","pid":0,"tid":4006434354,"ts":83428679979},{"cat":"function","dur":571,"name":"void __cdecl Pixel::EditorLayer::OnUpdate(class Pixel::Timestep)","ph":"X","pid":0,"tid":4006434354,"ts":83428688327},{"cat":"function","dur":635,"name":"void __cdecl Pixel::EditorLayer::OnUpdate(class Pixel::Timestep)","ph":"X","pid":0,"tid":4006434354,"ts":83428696780},{"cat":"function","dur":658,"name":"void __cdecl Pixel::EditorLayer::OnUpdate(class Pixel::Timestep)","ph":"X","pid":0,"tid":4006434354,"ts":83428704819},{"cat":"function","dur":745,"name":"void __cdecl Pixel::EditorLayer::OnUpdate(class Pixel::Timestep)","ph":"X","pid":0,"tid":4006434354,"ts":83428722309},{"cat":"function","dur":660,"name":"void __cdecl Pixel::EditorLayer::OnUpdate(class Pixel::Timestep)","ph":"X","pid":0,"tid":4006434354,"ts":83428729877},{"cat":"function","dur":705,"name":"void __cdecl Pixel::EditorLayer::OnUpdate(class Pixel::Timestep)","ph":"X","pid":0,"tid":4006434354,"ts":83428738417},{"cat":"function","dur":644,"name":"void __cdecl Pixel::EditorLayer::OnUpdate(class Pixel::Timestep)","ph":"X","pid":0,"tid":4006434354,"ts":83428746751},{"cat":"function","dur":617,"name":"void __cdecl Pixel::EditorLayer::OnUpdate(class Pixel::Timestep)","ph":"X","pid":0,"tid":4006434354,"ts":83428754971},{"cat":"function","dur":665,"name":"void __cdecl Pixel::EditorLayer::OnUpdate(class Pixel::Timestep)","ph":"X","pid":0,"tid":4006434354,"ts":83428763221},{"cat":"function","dur":692,"name":"void __cdecl Pixel::EditorLayer::OnUpdate(class Pixel::Timestep)","ph":"X","pid":0,"tid":4006434354,"ts":83428771537},{"cat":"function","dur":640,"name":"void __cdecl Pixel::EditorLayer::OnUpdate(class Pixel::Timestep)","ph":"X","pid":0,"tid":4006434354,"ts":83428780171},{"cat":"function","dur":653,"name":"void __cdecl Pixel::EditorLayer::OnUpdate(class Pixel::Timestep)","ph":"X","pid":0,"tid":4006434354,"ts":83428788211},{"cat":"function","dur":578,"name":"void __cdecl Pixel::EditorLayer::OnUpdate(class Pixel::Timestep)","ph":"X","pid":0,"tid":4006434354,"ts":83428796370},{"cat":"function","dur":671,"name":"void __cdecl Pixel::EditorLayer::OnUpdate(class Pixel::Timestep)","ph":"X","pid":0,"tid":4006434354,"ts":83428804884},{"cat":"function","dur":674,"name":"void __cdecl Pixel::EditorLayer::OnUpdate(class Pixel::Timestep)","ph":"X","pid":0,"tid":4006434354,"ts":83428814216},{"cat":"function","dur":647,"name":"void __cdecl Pixel::EditorLayer::OnUpdate(class Pixel::Timestep)","ph":"X","pid":0,"tid":4006434354,"ts":83428829538},{"cat":"function","dur":702,"name":"void __cdecl Pixel::EditorLayer::OnUpdate(class Pixel::Timestep)","ph":"X","pid":0,"tid":4006434354,"ts":83428838146},{"cat":"function","dur":1061,"name":"void __cdecl Pixel::EditorLayer::OnUpdate(class Pixel::Timestep)","ph":"X","pid":0,"tid":4006434354,"ts":83428846427},{"cat":"function","dur":654,"name":"void __cdecl Pixel::EditorLayer::OnUpdate(class Pixel::Timestep)","ph":"X","pid":0,"tid":4006434354,"ts":83428862719},{"cat":"function","dur":611,"name":"void __cdecl Pixel::EditorLayer::OnUpdate(class Pixel::Timestep)","ph":"X","pid":0,"tid":4006434354,"ts":83428871587},{"cat":"function","dur":707,"name":"void __cdecl Pixel::EditorLayer::OnUpdate(class Pixel::Timestep)","ph":"X","pid":0,"tid":4006434354,"ts":83428879949},{"cat":"function","dur":594,"name":"void __cdecl Pixel::EditorLayer::OnUpdate(class Pixel::Timestep)","ph":"X","pid":0,"tid":4006434354,"ts":83428888335},{"cat":"function","dur":540,"name":"void __cdecl Pixel::EditorLayer::OnUpdate(class Pixel::Timestep)","ph":"X","pid":0,"tid":4006434354,"ts":83428897475},{"cat":"function","dur":646,"name":"void __cdecl Pixel::EditorLayer::OnUpdate(class Pixel::Timestep)","ph":"X","pid":0,"tid":4006434354,"ts":83428904980},{"cat":"function","dur":634,"name":"void __cdecl Pixel::EditorLayer::OnUpdate(class Pixel::Timestep)","ph":"X","pid":0,"tid":4006434354,"ts":83428912992},{"cat":"function","dur":617,"name":"void __cdecl Pixel::EditorLayer::OnUpdate(class Pixel::Timestep)","ph":"X","pid":0,"tid":4006434354,"ts":83428921334},{"cat":"function","dur":740,"name":"void __cdecl Pixel::EditorLayer::OnUpdate(class Pixel::Timestep)","ph":"X","pid":0,"tid":4006434354,"ts":83428931250},{"cat":"function","dur":690,"name":"void __cdecl Pixel::EditorLayer::OnUpdate(class Pixel::Timestep)","ph":"X","pid":0,"tid":4006434354,"ts":83428938501},{"cat":"function","dur":642,"name":"void __cdecl Pixel::EditorLayer::OnUpdate(class Pixel::Timestep)","ph":"X","pid":0,"tid":4006434354,"ts":83428946406},{"cat":"function","dur":706,"name":"void __cdecl Pixel::EditorLayer::OnUpdate(class Pixel::Timestep)","ph":"X","pid":0,"tid":4006434354,"ts":83428955016},{"cat":"function","dur":568,"name":"void __cdecl Pixel::EditorLayer::OnUpdate(class Pixel::Timestep)","ph":"X","pid":0,"tid":4006434354,"ts":83428963354},{"cat":"function","dur":578,"name":"void __cdecl Pixel::EditorLayer::OnUpdate(class Pixel::Timestep)","ph":"X","pid":0,"tid":4006434354,"ts":83428972163},{"cat":"function","dur":649,"name":"void __cdecl Pixel::EditorLayer::OnUpdate(class Pixel::Timestep)","ph":"X","pid":0,"tid":4006434354,"ts":83428979981},{"cat":"function","dur":614,"name":"void __cdecl Pixel::EditorLayer::OnUpdate(class Pixel::Timestep)","ph":"X","pid":0,"tid":4006434354,"ts":83428988116},{"cat":"function","dur":607,"name":"void __cdecl Pixel::EditorLayer::OnUpdate(class Pixel::Timestep)","ph":"X","pid":0,"tid":4006434354,"ts":83428996305},{"cat":"function","dur":640,"name":"void __cdecl Pixel::EditorLayer::OnUpdate(class Pixel::Timestep)","ph":"X","pid":0,"tid":4006434354,"ts":83429004682},{"cat":"function","dur":622,"name":"void __cdecl Pixel::EditorLayer::OnUpdate(class Pixel::Timestep)","ph":"X","pid":0,"tid":4006434354,"ts":83429013045},{"cat":"function","dur":641,"name":"void __cdecl Pixel::EditorLayer::OnUpdate(class Pixel::Timestep)","ph":"X","pid":0,"tid":4006434354,"ts":83429029355},{"cat":"function","dur":785,"name":"void __cdecl Pixel::EditorLayer::OnUpdate(class Pixel::Timestep)","ph":"X","pid":0,"tid":4006434354,"ts":83429038037},{"cat":"function","dur":671,"name":"void __cdecl Pixel::EditorLayer::OnUpdate(class Pixel::Timestep)","ph":"X","pid":0,"tid":4006434354,"ts":83429046563},{"cat":"function","dur":741,"name":"void __cdecl Pixel::EditorLayer::OnUpdate(class Pixel::Timestep)","ph":"X","pid":0,"tid":4006434354,"ts":83429055040},{"cat":"function","dur":950,"name":"void __cdecl Pixel::EditorLayer::OnUpdate(class Pixel::Timestep)","ph":"X","pid":0,"tid":4006434354,"ts":83429063431},{"cat":"function","dur":579,"name":"void __cdecl Pixel::EditorLayer::OnUpdate(class Pixel::Timestep)","ph":"X","pid":0,"tid":4006434354,"ts":83429072181},{"cat":"function","dur":775,"name":"void __cdecl Pixel::EditorLayer::OnUpdate(class Pixel::Timestep)","ph":"X","pid":0,"tid":4006434354,"ts":83429080555},{"cat":"function","dur":735,"name":"void __cdecl Pixel::EditorLayer::OnUpdate(class Pixel::Timestep)","ph":"X","pid":0,"tid":4006434354,"ts":83429088385},{"cat":"function","dur":723,"name":"void __cdecl Pixel::EditorLayer::OnUpdate(class Pixel::Timestep)","ph":"X","pid":0,"tid":4006434354,"ts":83429096422},{"cat":"function","dur":659,"name":"void __cdecl Pixel::EditorLayer::OnUpdate(class Pixel::Timestep)","ph":"X","pid":0,"tid":4006434354,"ts":83429104776},{"cat":"function","dur":594,"name":"void __cdecl Pixel::EditorLayer::OnUpdate(class Pixel::Timestep)","ph":"X","pid":0,"tid":4006434354,"ts":83429113115},{"cat":"function","dur":737,"name":"void __cdecl Pixel::EditorLayer::OnUpdate(class Pixel::Timestep)","ph":"X","pid":0,"tid":4006434354,"ts":83429121519},{"cat":"function","dur":586,"name":"void __cdecl Pixel::EditorLayer::OnUpdate(class Pixel::Timestep)","ph":"X","pid":0,"tid":4006434354,"ts":83429137935},{"cat":"function","dur":1176,"name":"void __cdecl Pixel::EditorLayer::OnUpdate(class Pixel::Timestep)","ph":"X","pid":0,"tid":4006434354,"ts":83429146426},{"cat":"function","dur":1154,"name":"void __cdecl Pixel::EditorLayer::OnUpdate(class Pixel::Timestep)","ph":"X","pid":0,"tid":4006434354,"ts":83429154683},{"cat":"function","dur":1196,"name":"void __cdecl Pixel::EditorLayer::OnUpdate(class Pixel::Timestep)","ph":"X","pid":0,"tid":4006434354,"ts":83429171955},{"cat":"function","dur":1254,"name":"void __cdecl Pixel::EditorLayer::OnUpdate(class Pixel::Timestep)","ph":"X","pid":0,"tid":4006434354,"ts":83429179671},{"cat":"function","dur":1621,"name":"void __cdecl Pixel::EditorLayer::OnUpdate(class Pixel::Timestep)","ph":"X","pid":0,"tid":4006434354,"ts":83429195795},{"cat":"function","dur":1254,"name":"void __cdecl Pixel::EditorLayer::OnUpdate(class Pixel::Timestep)","ph":"X","pid":0,"tid":4006434354,"ts":83429212451},{"cat":"function","dur":1110,"name":"void __cdecl Pixel::EditorLayer::OnUpdate(class Pixel::Timestep)","ph":"X","pid":0,"tid":4006434354,"ts":83429221445},{"cat":"function","dur":1132,"name":"void __cdecl Pixel::EditorLayer::OnUpdate(class Pixel::Timestep)","ph":"X","pid":0,"tid":4006434354,"ts":83429237455},{"cat":"function","dur":591,"name":"void __cdecl Pixel::EditorLayer::OnUpdate(class Pixel::Timestep)","ph":"X","pid":0,"tid":4006434354,"ts":83429246418},{"cat":"function","dur":660,"name":"void __cdecl Pixel::EditorLayer::OnUpdate(class Pixel::Timestep)","ph":"X","pid":0,"tid":4006434354,"ts":83429262489},{"cat":"function","dur":668,"name":"void __cdecl Pixel::EditorLayer::OnUpdate(class Pixel::Timestep)","ph":"X","pid":0,"tid":4006434354,"ts":83429271402},{"cat":"function","dur":751,"name":"void __cdecl Pixel::EditorLayer::OnUpdate(class Pixel::Timestep)","ph":"X","pid":0,"tid":4006434354,"ts":83429279881},{"cat":"function","dur":579,"name":"void __cdecl Pixel::EditorLayer::OnUpdate(class Pixel::Timestep)","ph":"X","pid":0,"tid":4006434354,"ts":83429287982},{"cat":"function","dur":675,"name":"void __cdecl Pixel::EditorLayer::OnUpdate(class Pixel::Timestep)","ph":"X","pid":0,"tid":4006434354,"ts":83429296616},{"cat":"function","dur":646,"name":"void __cdecl Pixel::EditorLayer::OnUpdate(class Pixel::Timestep)","ph":"X","pid":0,"tid":4006434354,"ts":83429304791},{"cat":"function","dur":660,"name":"void __cdecl Pixel::EditorLayer::OnUpdate(class Pixel::Timestep)","ph":"X","pid":0,"tid":4006434354,"ts":83429313102},{"cat":"function","dur":649,"name":"void __cdecl Pixel::EditorLayer::OnUpdate(class Pixel::Timestep)","ph":"X","pid":0,"tid":4006434354,"ts":83429321555},{"cat":"function","dur":808,"name":"void __cdecl Pixel::EditorLayer::OnUpdate(class Pixel::Timestep)","ph":"X","pid":0,"tid":4006434354,"ts":83429337878},{"cat":"function","dur":663,"name":"void __cdecl Pixel::EditorLayer::OnUpdate(class Pixel::Timestep)","ph":"X","pid":0,"tid":4006434354,"ts":83429354638},{"cat":"function","dur":783,"name":"void __cdecl Pixel::EditorLayer::OnUpdate(class Pixel::Timestep)","ph":"X","pid":0,"tid":4006434354,"ts":83429370781},{"cat":"function","dur":666,"name":"void __cdecl Pixel::EditorLayer::OnUpdate(class Pixel::Timestep)","ph":"X","pid":0,"tid":4006434354,"ts":83429379937},{"cat":"function","dur":698,"name":"void __cdecl Pixel::EditorLayer::OnUpdate(class Pixel::Timestep)","ph":"X","pid":0,"tid":4006434354,"ts":83429388097},{"cat":"function","dur":703,"name":"void __cdecl Pixel::EditorLayer::OnUpdate(class Pixel::Timestep)","ph":"X","pid":0,"tid":4006434354,"ts":83429396501},{"cat":"function","dur":674,"name":"void __cdecl Pixel::EditorLayer::OnUpdate(class Pixel::Timestep)","ph":"X","pid":0,"tid":4006434354,"ts":83429404948},{"cat":"function","dur":624,"name":"void __cdecl Pixel::EditorLayer::OnUpdate(class Pixel::Timestep)","ph":"X","pid":0,"tid":4006434354,"ts":83429413170},{"cat":"function","dur":662,"name":"void __cdecl Pixel::EditorLayer::OnUpdate(class Pixel::Timestep)","ph":"X","pid":0,"tid":4006434354,"ts":83429421372},{"cat":"function","dur":615,"name":"void __cdecl Pixel::EditorLayer::OnUpdate(class Pixel::Timestep)","ph":"X","pid":0,"tid":4006434354,"ts":83429429920},{"cat":"function","dur":656,"name":"void __cdecl Pixel::EditorLayer::OnUpdate(class Pixel::Timestep)","ph":"X","pid":0,"tid":4006434354,"ts":83429438086},{"cat":"function","dur":599,"name":"void __cdecl Pixel::EditorLayer::OnUpdate(class Pixel::Timestep)","ph":"X","pid":0,"tid":4006434354,"ts":83429446309},{"cat":"function","dur":594,"name":"void __cdecl Pixel::EditorLayer::OnUpdate(class Pixel::Timestep)","ph":"X","pid":0,"tid":4006434354,"ts":83429454640},{"cat":"function","dur":609,"name":"void __cdecl Pixel::EditorLayer::OnUpdate(class Pixel::Timestep)","ph":"X","pid":0,"tid":4006434354,"ts":83429462992},{"cat":"function","dur":597,"name":"void __cdecl Pixel::EditorLayer::OnUpdate(class Pixel::Timestep)","ph":"X","pid":0,"tid":4006434354,"ts":83429479260},{"cat":"function","dur":639,"name":"void __cdecl Pixel::EditorLayer::OnUpdate(class Pixel::Timestep)","ph":"X","pid":0,"tid":4006434354,"ts":83429488033},{"cat":"function","dur":621,"name":"void __cdecl Pixel::EditorLayer::OnUpdate(class Pixel::Timestep)","ph":"X","pid":0,"tid":4006434354,"ts":83429496307},{"cat":"function","dur":581,"name":"void __cdecl Pixel::EditorLayer::OnUpdate(class Pixel::Timestep)","ph":"X","pid":0,"tid":4006434354,"ts":83429504536},{"cat":"function","dur":501,"name":"void __cdecl Pixel::EditorLayer::OnUpdate(class Pixel::Timestep)","ph":"X","pid":0,"tid":4006434354,"ts":83429512870},{"cat":"function","dur":641,"name":"void __cdecl Pixel::EditorLayer::OnUpdate(class Pixel::Timestep)","ph":"X","pid":0,"tid":4006434354,"ts":83429521234},{"cat":"function","dur":595,"name":"void __cdecl Pixel::EditorLayer::OnUpdate(class Pixel::Timestep)","ph":"X","pid":0,"tid":4006434354,"ts":83429529556},{"cat":"function","dur":550,"name":"void __cdecl Pixel::EditorLayer::OnUpdate(class Pixel::Timestep)","ph":"X","pid":0,"tid":4006434354,"ts":83429537980},{"cat":"function","dur":773,"name":"void __cdecl Pixel::EditorLayer::OnUpdate(class Pixel::Timestep)","ph":"X","pid":0,"tid":4006434354,"ts":83429546280},{"cat":"function","dur":603,"name":"void __cdecl Pixel::EditorLayer::OnUpdate(class Pixel::Timestep)","ph":"X","pid":0,"tid":4006434354,"ts":83429554761},{"cat":"function","dur":694,"name":"void __cdecl Pixel::EditorLayer::OnUpdate(class Pixel::Timestep)","ph":"X","pid":0,"tid":4006434354,"ts":83429564033},{"cat":"function","dur":653,"name":"void __cdecl Pixel::EditorLayer::OnUpdate(class Pixel::Timestep)","ph":"X","pid":0,"tid":4006434354,"ts":83429571793},{"cat":"function","dur":607,"name":"void __cdecl Pixel::EditorLayer::OnUpdate(class Pixel::Timestep)","ph":"X","pid":0,"tid":4006434354,"ts":83429579653},{"cat":"function","dur":630,"name":"void __cdecl Pixel::EditorLayer::OnUpdate(class Pixel::Timestep)","ph":"X","pid":0,"tid":4006434354,"ts":83429588147},{"cat":"function","dur":727,"name":"void __cdecl Pixel::EditorLayer::OnUpdate(class Pixel::Timestep)","ph":"X","pid":0,"tid":4006434354,"ts":83429604501},{"cat":"function","dur":579,"name":"void __cdecl Pixel::EditorLayer::OnUpdate(class Pixel::Timestep)","ph":"X","pid":0,"tid":4006434354,"ts":83429612970},{"cat":"function","dur":717,"name":"void __cdecl Pixel::EditorLayer::OnUpdate(class Pixel::Timestep)","ph":"X","pid":0,"tid":4006434354,"ts":83429621314},{"cat":"function","dur":673,"name":"void __cdecl Pixel::EditorLayer::OnUpdate(class Pixel::Timestep)","ph":"X","pid":0,"tid":4006434354,"ts":83429630154},{"cat":"function","dur":647,"name":"void __cdecl Pixel::EditorLayer::OnUpdate(class Pixel::Timestep)","ph":"X","pid":0,"tid":4006434354,"ts":83429638222},{"cat":"function","dur":686,"name":"void __cdecl Pixel::EditorLayer::OnUpdate(class Pixel::Timestep)","ph":"X","pid":0,"tid":4006434354,"ts":83429646656},{"cat":"function","dur":705,"name":"void __cdecl Pixel::EditorLayer::OnUpdate(class Pixel::Timestep)","ph":"X","pid":0,"tid":4006434354,"ts":83429655193},{"cat":"function","dur":752,"name":"void __cdecl Pixel::EditorLayer::OnUpdate(class Pixel::Timestep)","ph":"X","pid":0,"tid":4006434354,"ts":83429663378},{"cat":"function","dur":666,"name":"void __cdecl Pixel::EditorLayer::OnUpdate(class Pixel::Timestep)","ph":"X","pid":0,"tid":4006434354,"ts":83429671630},{"cat":"function","dur":624,"name":"void __cdecl Pixel::EditorLayer::OnUpdate(class Pixel::Timestep)","ph":"X","pid":0,"tid":4006434354,"ts":83429679870},{"cat":"function","dur":676,"name":"void __cdecl Pixel::EditorLayer::OnUpdate(class Pixel::Timestep)","ph":"X","pid":0,"tid":4006434354,"ts":83429688412},{"cat":"function","dur":648,"name":"void __cdecl Pixel::EditorLayer::OnUpdate(class Pixel::Timestep)","ph":"X","pid":0,"tid":4006434354,"ts":83429696856},{"cat":"function","dur":685,"name":"void __cdecl Pixel::EditorLayer::OnUpdate(class Pixel::Timestep)","ph":"X","pid":0,"tid":4006434354,"ts":83429705925},{"cat":"function","dur":594,"name":"void __cdecl Pixel::EditorLayer::OnUpdate(class Pixel::Timestep)","ph":"X","pid":0,"tid":4006434354,"ts":83429721359},{"cat":"function","dur":728,"name":"void __cdecl Pixel::EditorLayer::OnUpdate(class Pixel::Timestep)","ph":"X","pid":0,"tid":4006434354,"ts":83429730160},{"cat":"function","dur":664,"name":"void __cdecl Pixel::EditorLayer::OnUpdate(class Pixel::Timestep)","ph":"X","pid":0,"tid":4006434354,"ts":83429738563},{"cat":"function","dur":639,"name":"void __cdecl Pixel::EditorLayer::OnUpdate(class Pixel::Timestep)","ph":"X","pid":0,"tid":4006434354,"ts":83429746832},{"cat":"function","dur":702,"name":"void __cdecl Pixel::EditorLayer::OnUpdate(class Pixel::Timestep)","ph":"X","pid":0,"tid":4006434354,"ts":83429754843},{"cat":"function","dur":607,"name":"void __cdecl Pixel::EditorLayer::OnUpdate(class Pixel::Timestep)","ph":"X","pid":0,"tid":4006434354,"ts":83429771767},{"cat":"function","dur":773,"name":"void __cdecl Pixel::EditorLayer::OnUpdate(class Pixel::Timestep)","ph":"X","pid":0,"tid":4006434354,"ts":83429788190},{"cat":"function","dur":641,"name":"void __cdecl Pixel::EditorLayer::OnUpdate(class Pixel::Timestep)","ph":"X","pid":0,"tid":4006434354,"ts":83429796591},{"cat":"function","dur":698,"name":"void __cdecl Pixel::EditorLayer::OnUpdate(class Pixel::Timestep)","ph":"X","pid":0,"tid":4006434354,"ts":83429805049},{"cat":"function","dur":652,"name":"void __cdecl Pixel::EditorLayer::OnUpdate(class Pixel::Timestep)","ph":"X","pid":0,"tid":4006434354,"ts":83429820727},{"cat":"function","dur":663,"name":"void __cdecl Pixel::EditorLayer::OnUpdate(class Pixel::Timestep)","ph":"X","pid":0,"tid":4006434354,"ts":83429829819},{"cat":"function","dur":581,"name":"void __cdecl Pixel::EditorLayer::OnUpdate(class Pixel::Timestep)","ph":"X","pid":0,"tid":4006434354,"ts":83429838228},{"cat":"function","dur":684,"name":"void __cdecl Pixel::EditorLayer::OnUpdate(class Pixel::Timestep)","ph":"X","pid":0,"tid":4006434354,"ts":83429846527}]}